{
  "success": true,
  "totalCount": 176,
  "data": [
    {
      "nrc": "16789",
      "codigo": "FING-02001'",
      "profesor": "Por Asignar",
      "asignatura": "Álgebra Lineal.",
      "tax": "TA4",
      "mod": "PRE",
      "lun": "07:00/08:50",
      "mar": null,
      "mie": "07:00/09:50",
      "jue": null,
      "vie": null,
      "sab": null,
      "dom": null
    },
    {
      "nrc": "16790",
      "codigo": "FING-'02001'",
      "profesor": "Por Asignar",
      "asignatura": "Álgebra Lineal.",
      "tax": "TA4",
      "mod": "PRE",
      "lun": null,
      "mar": "13:00/14:50",
      "mie": null,
      "jue": null,
      "vie": "13:00/15:50",
      "sab": null,
      "dom": null
    },
    {
      "nrc": "15549",
      "codigo": "FING-'02002'",
      "profesor": "Quintero Davila, José Luis",
      "asignatura": "Álgebra y Trigonometría.",
      "tax": "TA4",
      "mod": "PRE",
      "lun": null,
      "mar": "16:00/17:50",
      "mie": null,
      "jue": "16:00/17:50",
      "vie": null,
      "sab": null,
      "dom": null
    },
    {
      "nrc": "17255",
      "codigo": "FING-'02002'",
      "profesor": "Por Asignar",
      "asignatura": "Álgebra y Trigonometría.",
      "tax": "TA4",
      "mod": "PRE",
      "lun": "09:00/10:50",
      "mar": null,
      "mie": null,
      "jue": null,
      "vie": "09:00/10:50",
      "sab": null,
      "dom": null
    },
    {
      "nrc": "15847",
      "codigo": "INFO-'02002'",
      "profesor": "Hernández Barrera, Omar Jesús",
      "asignatura": "Algoritmos y Estructuras de Datos.",
      "tax": "TA9",
      "mod": "PRE",
      "lun": null,
      "mar": "15:00/16:50",
      "mie": "13:00/16:50",
      "jue": null,
      "vie": null,
      "sab": null,
      "dom": null
    },
    {
      "nrc": "15848",
      "codigo": "INFO-'02002'",
      "profesor": "Hernández Barrera, Omar Jesús",
      "asignatura": "Algoritmos y Estructuras de Datos.",
      "tax": "TA9",
      "mod": "PRE",
      "lun": null,
      "mar": null,
      "mie": "08:00/09:50",
      "jue": null,
      "vie": "08:00/11:50",
      "sab": null,
      "dom": null
    },
    {
      "nrc": "15849",
      "codigo": "INFO-'02002'",
      "profesor": "Hernández Barrera, Omar Jesús",
      "asignatura": "Algoritmos y Estructuras de Datos.",
      "tax": "TA9",
      "mod": "PRE",
      "lun": "13:00/14:50",
      "mar": null,
      "mie": null,
      "jue": "13:00/16:50",
      "vie": null,
      "sab": null,
      "dom": null
    },
    {
      "nrc": "15850",
      "codigo": "INFO-'02002'",
      "profesor": "Mendoza, Lia Roxana",
      "asignatura": "Algoritmos y Estructuras de Datos.",
      "tax": "TA9",
      "mod": "PRE",
      "lun": null,
      "mar": "13:00/16:50",
      "mie": "15:00/16:50",
      "jue": null,
      "vie": null,
      "sab": null,
      "dom": null
    },
    {
      "nrc": "15851",
      "codigo": "INFO-'02002'",
      "profesor": "León Espinoza, Yisheng",
      "asignatura": "Algoritmos y Estructuras de Datos.",
      "tax": "TA9",
      "mod": "PRE",
      "lun": null,
      "mar": null,
      "mie": "08:00/09:50",
      "jue": null,
      "vie": "08:00/11:50",
      "sab": null,
      "dom": null
    },
    {
      "nrc": "15865",
      "codigo": "INFO-'02002'",
      "profesor": "Fuentes Salazar, Luis Reynaldo",
      "asignatura": "Algoritmos y Estructuras de Datos.",
      "tax": "TA9",
      "mod": "PRE",
      "lun": "13:00/14:50",
      "mar": "10:00/11:50  13:00/14:50",
      "mie": null,
      "jue": null,
      "vie": null,
      "sab": null,
      "dom": null
    },
    {
      "nrc": "15991",
      "codigo": "INFO-'02002'",
      "profesor": "Meza Houtteman, Oscar José",
      "asignatura": "Algoritmos y Estructuras de Datos.",
      "tax": "TA9",
      "mod": "PRE",
      "lun": "13:00/16:50",
      "mar": null,
      "mie": null,
      "jue": null,
      "vie": "09:00/10:50",
      "sab": null,
      "dom": null
    },
    {
      "nrc": "15842",
      "codigo": "INFO-'02001'",
      "profesor": "Holguín Valdez, Rodolfo Enrique",
      "asignatura": "Algoritmos y Programación.",
      "tax": "TA9",
      "mod": "PRE",
      "lun": "07:00/09:50",
      "mar": null,
      "mie": null,
      "jue": null,
      "vie": null,
      "sab": null,
      "dom": null
    },
    {
      "nrc": "15843",
      "codigo": "INFO-'02001'",
      "profesor": "Castillo Pacheco, José Gregorio",
      "asignatura": "Algoritmos y Programación.",
      "tax": "TA9",
      "mod": "PRE",
      "lun": null,
      "mar": "10:00/12:50",
      "mie": null,
      "jue": null,
      "vie": null,
      "sab": null,
      "dom": null
    },
    {
      "nrc": "15844",
      "codigo": "INFO-'02001'",
      "profesor": "Visconti Montemarano, Italo",
      "asignatura": "Algoritmos y Programación.",
      "tax": "TA9",
      "mod": "PRE",
      "lun": null,
      "mar": null,
      "mie": "10:00/12:50",
      "jue": null,
      "vie": null,
      "sab": null,
      "dom": null
    },
    {
      "nrc": "16425",
      "codigo": "INFO-'02015'",
      "profesor": "Ruíz Rondón, Eva Alexandra",
      "asignatura": "Arquitectura del Computador Aplicada.",
      "tax": "TA9",
      "mod": "PRE",
      "lun": "17:00/18:50",
      "mar": "16:00/17:50",
      "mie": null,
      "jue": null,
      "vie": null,
      "sab": null,
      "dom": null
    },
    {
      "nrc": "16426",
      "codigo": "INFO-'02015'",
      "profesor": "Murillo Gonzalez, Luz Karime",
      "asignatura": "Arquitectura del Computador Aplicada.",
      "tax": "TA9",
      "mod": "PRE",
      "lun": null,
      "mar": "07:00/08:50",
      "mie": null,
      "jue": null,
      "vie": "13:00/14:50",
      "sab": null,
      "dom": null
    },
    {
      "nrc": "16427",
      "codigo": "INFO-'P2015'",
      "profesor": "Ruíz Rondón, Eva Alexandra",
      "asignatura": "Arquitectura del Computador Aplicada (Práctica).",
      "tax": "TA0",
      "mod": "PRE",
      "lun": "13:00/14:50",
      "mar": null,
      "mie": null,
      "jue": null,
      "vie": null,
      "sab": null,
      "dom": null
    },
    {
      "nrc": "16429",
      "codigo": "INFO-'P2015'",
      "profesor": "Ruíz Rondón, Eva Alexandra",
      "asignatura": "Arquitectura del Computador Aplicada (Práctica).",
      "tax": "TA0",
      "mod": "PRE",
      "lun": "15:00/16:50",
      "mar": null,
      "mie": null,
      "jue": null,
      "vie": null,
      "sab": null,
      "dom": null
    },
    {
      "nrc": "16797",
      "codigo": "INFO-'P2015'",
      "profesor": "Ruíz Rondón, Eva Alexandra",
      "asignatura": "Arquitectura del Computador Aplicada (Práctica).",
      "tax": "TA0",
      "mod": "PRE",
      "lun": null,
      "mar": "14:00/15:50",
      "mie": null,
      "jue": null,
      "vie": null,
      "sab": null,
      "dom": null
    },
    {
      "nrc": "16701",
      "codigo": "INFO-'02029'",
      "profesor": "Ortega, Dinarle Milagro",
      "asignatura": "Arquitecturas Empresariales.",
      "tax": "TA4E",
      "mod": "VIT",
      "lun": null,
      "mar": null,
      "mie": null,
      "jue": null,
      "vie": null,
      "sab": "16:00/18:50",
      "dom": null
    },
    {
      "nrc": "15858",
      "codigo": "INFO-'02019'",
      "profesor": "Suárez, Ernesto",
      "asignatura": "Aseguramiento de la Calidad del Software.",
      "tax": "TA4E",
      "mod": "PRE",
      "lun": "10:00/12:50",
      "mar": null,
      "mie": null,
      "jue": null,
      "vie": null,
      "sab": null,
      "dom": null
    },
    {
      "nrc": "16849",
      "codigo": "INFO-'02019'",
      "profesor": "Suárez, Ernesto",
      "asignatura": "Aseguramiento de la Calidad del Software.",
      "tax": "TA4E",
      "mod": "PRE",
      "lun": "13:00/15:50",
      "mar": null,
      "mie": null,
      "jue": null,
      "vie": null,
      "sab": null,
      "dom": null
    },
    {
      "nrc": "15555",
      "codigo": "FING-'02003'",
      "profesor": "Cardenas Cardenas, Augusto José",
      "asignatura": "Cálculo Diferencial.",
      "tax": "TA4",
      "mod": "PRE",
      "lun": null,
      "mar": null,
      "mie": "11:00/13:50",
      "jue": "13:00/14:50",
      "vie": null,
      "sab": null,
      "dom": null
    },
    {
      "nrc": "16786",
      "codigo": "FING-'02003'",
      "profesor": "Por Asignar",
      "asignatura": "Cálculo Diferencial.",
      "tax": "TA4",
      "mod": "PRE",
      "lun": null,
      "mar": "07:00/08:50",
      "mie": null,
      "jue": "07:00/09:50",
      "vie": null,
      "sab": null,
      "dom": null
    },
    {
      "nrc": "16787",
      "codigo": "FING-'02004'",
      "profesor": "Por Asignar",
      "asignatura": "Cálculo Integral.",
      "tax": "TA4",
      "mod": "PRE",
      "lun": null,
      "mar": null,
      "mie": "07:00/08:50",
      "jue": "07:00/08:50",
      "vie": null,
      "sab": null,
      "dom": null
    },
    {
      "nrc": "16788",
      "codigo": "FING-'02004'",
      "profesor": "Por Asignar",
      "asignatura": "Cálculo Integral.",
      "tax": "TA4",
      "mod": "PRE",
      "lun": null,
      "mar": null,
      "mie": "14:00/15:50",
      "jue": "16:00/17:50",
      "vie": null,
      "sab": null,
      "dom": null
    },
    {
      "nrc": "16791",
      "codigo": "FING-'02005'",
      "profesor": "Por Asignar",
      "asignatura": "Cálculo Vectorial.",
      "tax": "TA4",
      "mod": "PRE",
      "lun": null,
      "mar": "11:00/12:50",
      "mie": "09:00/10:50",
      "jue": null,
      "vie": null,
      "sab": null,
      "dom": null
    },
    {
      "nrc": "15852",
      "codigo": "INFO-'02023'",
      "profesor": "Ferrer Zapata, Francis Elena",
      "asignatura": "Ciberseguridad.",
      "tax": "TA9",
      "mod": "PRE",
      "lun": "15:00/16:50",
      "mar": null,
      "mie": null,
      "jue": null,
      "vie": null,
      "sab": null,
      "dom": null
    },
    {
      "nrc": "16018",
      "codigo": "INFO-'P2023'",
      "profesor": "Ferrer Zapata, Francis Elena",
      "asignatura": "Ciberseguridad (Práctica).",
      "tax": "TA0",
      "mod": "PRE",
      "lun": null,
      "mar": null,
      "mie": null,
      "jue": "07:00/08:50",
      "vie": null,
      "sab": null,
      "dom": null
    },
    {
      "nrc": "16702",
      "codigo": "INFO-'P2023'",
      "profesor": "Lara Domínguez, Gustavo Adolfo",
      "asignatura": "Ciberseguridad (Práctica).",
      "tax": "TA0",
      "mod": "PRE",
      "lun": null,
      "mar": null,
      "mie": null,
      "jue": null,
      "vie": "08:00/09:50",
      "sab": null,
      "dom": null
    },
    {
      "nrc": "17161",
      "codigo": "UCAB-'00009'",
      "profesor": "Por Asignar",
      "asignatura": "Competencia Textual en Español.",
      "tax": "TA6",
      "mod": "PRE",
      "lun": "07:00/07:50",
      "mar": null,
      "mie": "11:00/11:50",
      "jue": null,
      "vie": null,
      "sab": null,
      "dom": null
    },
    {
      "nrc": "15838",
      "codigo": "INFO-'02028'",
      "profesor": "Rodríguez Rojas, Rómulo José",
      "asignatura": "Computación en la Nube.",
      "tax": "TA9",
      "mod": "PRE",
      "lun": "16:00/17:50",
      "mar": null,
      "mie": null,
      "jue": null,
      "vie": null,
      "sab": null,
      "dom": null
    },
    {
      "nrc": "15873",
      "codigo": "INFO-'P2028'",
      "profesor": "Rodríguez Rojas, Rómulo José",
      "asignatura": "Computación en la Nube (Práctica).",
      "tax": "TA0",
      "mod": "PRE",
      "lun": null,
      "mar": "16:00/17:50",
      "mie": null,
      "jue": null,
      "vie": null,
      "sab": null,
      "dom": null
    },
    {
      "nrc": "15874",
      "codigo": "INFO-'P2028'",
      "profesor": "Rodríguez Rojas, Rómulo José",
      "asignatura": "Computación en la Nube (Práctica).",
      "tax": "TA0",
      "mod": "PRE",
      "lun": null,
      "mar": null,
      "mie": null,
      "jue": "16:00/17:50",
      "vie": null,
      "sab": null,
      "dom": null
    },
    {
      "nrc": "17187",
      "codigo": "UCAB-'02002'",
      "profesor": "Por Asignar",
      "asignatura": "Consultoría y Marca Personal.",
      "tax": "TA1",
      "mod": "PRE",
      "lun": null,
      "mar": null,
      "mie": null,
      "jue": null,
      "vie": null,
      "sab": null,
      "dom": null
    },
    {
      "nrc": "15335",
      "codigo": "FACE-'00024'",
      "profesor": "Lobo Zambrano, Antonio Ramón",
      "asignatura": "Contabilidad Financiera.",
      "tax": "TA3",
      "mod": "PRE",
      "lun": null,
      "mar": "11:00/12:50",
      "mie": null,
      "jue": "10:00/11:50",
      "vie": null,
      "sab": null,
      "dom": null
    },
    {
      "nrc": "15336",
      "codigo": "FACE-'00024'",
      "profesor": "Ávila Dos Ramos, Rafael José",
      "asignatura": "Contabilidad Financiera.",
      "tax": "TA3",
      "mod": "PRE",
      "lun": "11:00/12:50",
      "mar": "07:00/08:50",
      "mie": null,
      "jue": null,
      "vie": null,
      "sab": null,
      "dom": null
    },
    {
      "nrc": "15337",
      "codigo": "FACE-'00024'",
      "profesor": "Rodríguez Rodríguez, Bricelis Rosa",
      "asignatura": "Contabilidad Financiera.",
      "tax": "TA3",
      "mod": "PRE",
      "lun": null,
      "mar": "13:00/14:50",
      "mie": null,
      "jue": null,
      "vie": "13:00/14:50",
      "sab": null,
      "dom": null
    },
    {
      "nrc": "15484",
      "codigo": "FACE-'00024'",
      "profesor": "Márquez Lugo, Reinaldo José",
      "asignatura": "Contabilidad Financiera.",
      "tax": "TA3",
      "mod": "PRE",
      "lun": "17:00/18:50",
      "mar": "17:00/18:50",
      "mie": null,
      "jue": null,
      "vie": null,
      "sab": null,
      "dom": null
    },
    {
      "nrc": "15724",
      "codigo": "FACE-'00024'",
      "profesor": "García Lovera, Nahomi Andrea",
      "asignatura": "Contabilidad Financiera.",
      "tax": "TA3",
      "mod": "PRE",
      "lun": "17:00/18:50",
      "mar": null,
      "mie": "17:00/18:50",
      "jue": null,
      "vie": null,
      "sab": null,
      "dom": null
    },
    {
      "nrc": "16116",
      "codigo": "LETR-'02030'",
      "profesor": "Fulco Salazar, Fabiola Isabel",
      "asignatura": "Creación en Medios Digitales.",
      "tax": "TA6E",
      "mod": "VIT",
      "lun": null,
      "mar": null,
      "mie": null,
      "jue": null,
      "vie": null,
      "sab": "07:00/09:50",
      "dom": null
    },
    {
      "nrc": "15853",
      "codigo": "INFO-'02025'",
      "profesor": "Alonzo Sánchez, Carlos Eduardo",
      "asignatura": "Desarrollo de Software.",
      "tax": "TA4E",
      "mod": "PRE",
      "lun": null,
      "mar": null,
      "mie": null,
      "jue": "09:00/10:50",
      "vie": "16:00/17:50",
      "sab": null,
      "dom": null
    },
    {
      "nrc": "16408",
      "codigo": "INFO-'02025'",
      "profesor": "Ponce Mavárez, Bismarck Ricardo",
      "asignatura": "Desarrollo de Software.",
      "tax": "TA4E",
      "mod": "PRE",
      "lun": "18:00/19:50",
      "mar": null,
      "mie": null,
      "jue": null,
      "vie": "16:00/17:50",
      "sab": null,
      "dom": null
    },
    {
      "nrc": "15007",
      "codigo": "UCAB-'00003'",
      "profesor": "Cristian López, Carmen Teresa",
      "asignatura": "Ecología, Ambiente y Sustentabilidad.",
      "tax": "TA1",
      "mod": "PRE",
      "lun": null,
      "mar": "09:00/10:50",
      "mie": null,
      "jue": null,
      "vie": null,
      "sab": null,
      "dom": null
    },
    {
      "nrc": "15008",
      "codigo": "UCAB-'00003'",
      "profesor": "Soledad Rodríguez, Beatriz Elena",
      "asignatura": "Ecología, Ambiente y Sustentabilidad.",
      "tax": "TA1",
      "mod": "PRE",
      "lun": null,
      "mar": "15:00/16:50",
      "mie": null,
      "jue": null,
      "vie": null,
      "sab": null,
      "dom": null
    },
    {
      "nrc": "15009",
      "codigo": "UCAB-'00003'",
      "profesor": "Benitez Maal, Joaquín Patricio",
      "asignatura": "Ecología, Ambiente y Sustentabilidad.",
      "tax": "TA1",
      "mod": "PRE",
      "lun": null,
      "mar": null,
      "mie": "09:00/10:50",
      "jue": null,
      "vie": null,
      "sab": null,
      "dom": null
    },
    {
      "nrc": "15012",
      "codigo": "UCAB-'00003'",
      "profesor": "Méndez de Carrera, Debbie Elizabeth",
      "asignatura": "Ecología, Ambiente y Sustentabilidad.",
      "tax": "TA1",
      "mod": "PRE",
      "lun": null,
      "mar": null,
      "mie": null,
      "jue": "09:00/10:50",
      "vie": null,
      "sab": null,
      "dom": null
    },
    {
      "nrc": "15881",
      "codigo": "UCAB-'00003'",
      "profesor": "Iskandar Nahas, Laila",
      "asignatura": "Ecología, Ambiente y Sustentabilidad.",
      "tax": "TA1",
      "mod": "PRE",
      "lun": null,
      "mar": null,
      "mie": null,
      "jue": null,
      "vie": "09:00/10:50",
      "sab": null,
      "dom": null
    },
    {
      "nrc": "16058",
      "codigo": "UCAB-'00003'",
      "profesor": "Sánchez Castellanos, Douglas Antonio",
      "asignatura": "Ecología, Ambiente y Sustentabilidad.",
      "tax": "TA1",
      "mod": "PRE",
      "lun": null,
      "mar": null,
      "mie": null,
      "jue": null,
      "vie": "14:00/15:50",
      "sab": null,
      "dom": null
    },
    {
      "nrc": "15562",
      "codigo": "FING-'02006'",
      "profesor": "Estrada, Luis Enrique",
      "asignatura": "Ecuaciones Diferenciales Ordinarias.",
      "tax": "TA4",
      "mod": "PRE",
      "lun": null,
      "mar": null,
      "mie": null,
      "jue": "07:00/08:50",
      "vie": "13:00/13:50",
      "sab": null,
      "dom": null
    },
    {
      "nrc": "16792",
      "codigo": "FING-'02006'",
      "profesor": "Por Asignar",
      "asignatura": "Ecuaciones Diferenciales Ordinarias.",
      "tax": "TA4",
      "mod": "PRE",
      "lun": null,
      "mar": null,
      "mie": null,
      "jue": null,
      "vie": "13:00/15:50",
      "sab": null,
      "dom": null
    },
    {
      "nrc": "15875",
      "codigo": "INFO-'82002'",
      "profesor": "Castillo Pacheco, José Gregorio",
      "asignatura": "Electiva: Desarrollo de APIs con Python.",
      "tax": "TA8",
      "mod": "PRE",
      "lun": null,
      "mar": "07:00/09:50",
      "mie": null,
      "jue": null,
      "vie": null,
      "sab": null,
      "dom": null
    },
    {
      "nrc": "15503",
      "codigo": "FING-'80425'",
      "profesor": "Fernandes Agrela, Ana Karina",
      "asignatura": "Electiva: Desarrollo de Software Fintech.",
      "tax": "TA8",
      "mod": "PRE",
      "lun": null,
      "mar": "12:00/14:50",
      "mie": null,
      "jue": null,
      "vie": null,
      "sab": null,
      "dom": null
    },
    {
      "nrc": "15876",
      "codigo": "INFO-'82001'",
      "profesor": "Gómez Chacón, Carlos Esteban",
      "asignatura": "Electiva: Desarrollo de Videojuegos con Unity.",
      "tax": "TA8",
      "mod": "PRE",
      "lun": null,
      "mar": null,
      "mie": "08:00/10:50",
      "jue": null,
      "vie": null,
      "sab": null,
      "dom": null
    },
    {
      "nrc": "16975",
      "codigo": "TELE-'82002'",
      "profesor": "Level Manzo, Eudys Alexander",
      "asignatura": "Electiva: Implementación de Redes Cisco.",
      "tax": "TA8",
      "mod": "PRE",
      "lun": null,
      "mar": "13:00/15:50",
      "mie": null,
      "jue": null,
      "vie": null,
      "sab": null,
      "dom": null
    },
    {
      "nrc": "15955",
      "codigo": "UCAB-'80011'",
      "profesor": "Almeida Franca, Luis Alberto",
      "asignatura": "Electiva: Inglés Intercultural.",
      "tax": "TA6",
      "mod": "PRE",
      "lun": null,
      "mar": null,
      "mie": null,
      "jue": null,
      "vie": "13:00/14:50",
      "sab": null,
      "dom": null
    },
    {
      "nrc": "16844",
      "codigo": "UCAB-'80012'",
      "profesor": "Villarroel Flores, Valeska Emilia",
      "asignatura": "Electiva: Inglés para Entornos Globales.",
      "tax": "TA6",
      "mod": "PRE",
      "lun": null,
      "mar": null,
      "mie": "15:00/16:50",
      "jue": null,
      "vie": null,
      "sab": null,
      "dom": null
    },
    {
      "nrc": "16949",
      "codigo": "INFO-'82004'",
      "profesor": "Russoniello Antonacci, Antonio",
      "asignatura": "Electiva: Internet de las Cosas.",
      "tax": "TA8",
      "mod": "PRE",
      "lun": null,
      "mar": null,
      "mie": null,
      "jue": "15:00/17:50",
      "vie": null,
      "sab": null,
      "dom": null
    },
    {
      "nrc": "16951",
      "codigo": "INFO-'82003'",
      "profesor": "Russoniello Antonacci, Antonio",
      "asignatura": "Electiva: Introducción a la Blockchain.",
      "tax": "TA4E",
      "mod": "PRE",
      "lun": null,
      "mar": null,
      "mie": null,
      "jue": "11:00/13:50",
      "vie": null,
      "sab": null,
      "dom": null
    },
    {
      "nrc": "15879",
      "codigo": "UCAB-'80008'",
      "profesor": "Alba Álvarez, María Gabriela",
      "asignatura": "Electiva: Introducción al Idioma Italiano.",
      "tax": "TA6",
      "mod": "PRE",
      "lun": null,
      "mar": null,
      "mie": null,
      "jue": "13:00/14:50",
      "vie": null,
      "sab": null,
      "dom": null
    },
    {
      "nrc": "15954",
      "codigo": "UCAB-'80010'",
      "profesor": "Tavares Lourenco, Ricardo",
      "asignatura": "Electiva: Introducción al Idioma Portugués.",
      "tax": "TA6",
      "mod": "PRE",
      "lun": null,
      "mar": "09:00/10:50",
      "mie": null,
      "jue": null,
      "vie": null,
      "sab": null,
      "dom": null
    },
    {
      "nrc": "17289",
      "codigo": "ECON-'8I003'",
      "profesor": "Hernandez Angarita, Hugo Guillermo",
      "asignatura": "Electiva: Introduction to Data Science.",
      "tax": "TA8",
      "mod": "LIN",
      "lun": "07:00/08:50",
      "mar": null,
      "mie": null,
      "jue": null,
      "vie": null,
      "sab": null,
      "dom": null
    },
    {
      "nrc": "16838",
      "codigo": "UCAB-'80009'",
      "profesor": "Jung, Mikyoung Rebecca",
      "asignatura": "Electiva: Introducción al Coreano.",
      "tax": "TA6",
      "mod": "PRE",
      "lun": null,
      "mar": "14:00/15:50",
      "mie": null,
      "jue": null,
      "vie": null,
      "sab": null,
      "dom": null
    },
    {
      "nrc": "16839",
      "codigo": "UCAB-'80014'",
      "profesor": "Rodriguez Carrillo, Karen Heleana",
      "asignatura": "Electiva: Introducción al Francés.",
      "tax": "TA6",
      "mod": "PRE",
      "lun": null,
      "mar": "12:00/13:50 EC-18",
      "mie": null,
      "jue": null,
      "vie": null,
      "sab": null,
      "dom": null
    },
    {
      "nrc": "16528",
      "codigo": "CISO-'80560'",
      "profesor": "De Faria Freitas, Christopher Orlando",
      "asignatura": "Electiva: Auxilio Médico Integral.",
      "tax": "TA8",
      "mod": "PRE",
      "lun": null,
      "mar": "13:00/15:50",
      "mie": null,
      "jue": null,
      "vie": null,
      "sab": null,
      "dom": null
    },
    {
      "nrc": "17264",
      "codigo": "INDU-'82001'",
      "profesor": "Henríquez Acosta, Diego Ignacio",
      "asignatura": "Electiva: Movilidad Eléctrica.",
      "tax": "TA9",
      "mod": "PRE",
      "lun": null,
      "mar": null,
      "mie": null,
      "jue": null,
      "vie": null,
      "sab": "08:00/09:50  11:00/13:50",
      "dom": null
    },
    {
      "nrc": "17033",
      "codigo": "FING-'02007'",
      "profesor": "Por Asignar",
      "asignatura": "Electricidad y Magnetismo.",
      "tax": "TA4",
      "mod": "PRE",
      "lun": "15:00/16:50",
      "mar": null,
      "mie": null,
      "jue": null,
      "vie": "07:00/09:50",
      "sab": null,
      "dom": null
    },
    {
      "nrc": "16793",
      "codigo": "FING-'02014'",
      "profesor": "Por Asignar",
      "asignatura": "Ética Profesional.",
      "tax": "TA2",
      "mod": "VIT",
      "lun": null,
      "mar": null,
      "mie": null,
      "jue": "19:00/20:50",
      "vie": null,
      "sab": null,
      "dom": null
    },
    {
      "nrc": "15841",
      "codigo": "INFO-'02027'",
      "profesor": "Madrid Rodríguez, Juan Aldemaro",
      "asignatura": "Evaluación de Sistemas Informáticos.",
      "tax": "TA4E",
      "mod": "VIT",
      "lun": null,
      "mar": null,
      "mie": null,
      "jue": null,
      "vie": null,
      "sab": "19:00/21:50",
      "dom": null
    },
    {
      "nrc": "15688",
      "codigo": "FING-'02015'",
      "profesor": "Peraza Cabello, Francisco José",
      "asignatura": "Física General.",
      "tax": "TA4",
      "mod": "PRE",
      "lun": null,
      "mar": null,
      "mie": "16:00/17:50",
      "jue": "13:00/15:50",
      "vie": null,
      "sab": null,
      "dom": null
    },
    {
      "nrc": "16413",
      "codigo": "FING-'02015'",
      "profesor": "Por Asignar",
      "asignatura": "Física General.",
      "tax": "TA4",
      "mod": "PRE",
      "lun": "11:00/13:50",
      "mar": null,
      "mie": null,
      "jue": null,
      "vie": "11:00/12:50",
      "sab": null,
      "dom": null
    },
    {
      "nrc": "16578",
      "codigo": "FING-'02015'",
      "profesor": "Por Asignar",
      "asignatura": "Física General.",
      "tax": "TA4",
      "mod": "PRE",
      "lun": "13:00/14:50",
      "mar": "10:00/12:50",
      "mie": null,
      "jue": null,
      "vie": null,
      "sab": null,
      "dom": null
    },
    {
      "nrc": "15627",
      "codigo": "FING-'02008'",
      "profesor": "Castillo Pacheco, José Gregorio",
      "asignatura": "Fundamentos de Programación.",
      "tax": "TA9",
      "mod": "PRE",
      "lun": "08:00/10:50",
      "mar": null,
      "mie": null,
      "jue": null,
      "vie": null,
      "sab": null,
      "dom": null
    },
    {
      "nrc": "15628",
      "codigo": "FING-'02008'",
      "profesor": "Holguín Valdez, Rodolfo Enrique",
      "asignatura": "Fundamentos de Programación.",
      "tax": "TA9",
      "mod": "PRE",
      "lun": "14:00/16:50",
      "mar": null,
      "mie": null,
      "jue": null,
      "vie": null,
      "sab": null,
      "dom": null
    },
    {
      "nrc": "16093",
      "codigo": "FING-'02008'",
      "profesor": "Castillo Pacheco, José Gregorio",
      "asignatura": "Fundamentos de Programación.",
      "tax": "TA9",
      "mod": "PRE",
      "lun": null,
      "mar": null,
      "mie": null,
      "jue": "07:00/09:50",
      "vie": null,
      "sab": null,
      "dom": null
    },
    {
      "nrc": "16095",
      "codigo": "FING-'02008'",
      "profesor": "Zambrano Camero, Katiuska del Carmen",
      "asignatura": "Fundamentos de Programación.",
      "tax": "TA9",
      "mod": "PRE",
      "lun": null,
      "mar": "11:00/13:50",
      "mie": null,
      "jue": null,
      "vie": null,
      "sab": null,
      "dom": null
    },
    {
      "nrc": "17156",
      "codigo": "FING-'02008'",
      "profesor": "Holguín Valdez, Rodolfo Enrique",
      "asignatura": "Fundamentos de Programación.",
      "tax": "TA9",
      "mod": "PRE",
      "lun": null,
      "mar": null,
      "mie": "10:00/12:50",
      "jue": null,
      "vie": null,
      "sab": null,
      "dom": null
    },
    {
      "nrc": "15825",
      "codigo": "INFO-'02013'",
      "profesor": "Hernández de López, Fanny Xiomara",
      "asignatura": "Gestión de Proyectos de Software.",
      "tax": "TA4E",
      "mod": "VIT",
      "lun": "19:00/21:50",
      "mar": null,
      "mie": null,
      "jue": null,
      "vie": null,
      "sab": null,
      "dom": null
    },
    {
      "nrc": "16495",
      "codigo": "INFO-'02013'",
      "profesor": "Hernández de López, Fanny Xiomara",
      "asignatura": "Gestión de Proyectos de Software.",
      "tax": "TA4E",
      "mod": "VIT",
      "lun": null,
      "mar": null,
      "mie": "19:00/21:50",
      "jue": null,
      "vie": null,
      "sab": null,
      "dom": null
    },
    {
      "nrc": "15001",
      "codigo": "UCAB-'00001'",
      "profesor": "García, Ana María",
      "asignatura": "Identidad, Liderazgo y Compromiso I.",
      "tax": "TA1",
      "mod": "PRE",
      "lun": "11:00/12:50",
      "mar": null,
      "mie": null,
      "jue": null,
      "vie": null,
      "sab": null,
      "dom": null
    },
    {
      "nrc": "15600",
      "codigo": "UCAB-'00001'",
      "profesor": "Camacho Mujica, Yuleima del Carmen",
      "asignatura": "Identidad, Liderazgo y Compromiso I.",
      "tax": "TA1",
      "mod": "PRE",
      "lun": null,
      "mar": "11:00/12:50",
      "mie": null,
      "jue": null,
      "vie": null,
      "sab": null,
      "dom": null
    },
    {
      "nrc": "16166",
      "codigo": "UCAB-'00001'",
      "profesor": "Por Asignar",
      "asignatura": "Identidad, Liderazgo y Compromiso I.",
      "tax": "TA1",
      "mod": "PRE",
      "lun": null,
      "mar": null,
      "mie": "11:00/12:50",
      "jue": null,
      "vie": null,
      "sab": null,
      "dom": null
    },
    {
      "nrc": "16167",
      "codigo": "UCAB-'00001'",
      "profesor": "Torres, Richard Alexis",
      "asignatura": "Identidad, Liderazgo y Compromiso I.",
      "tax": "TA1",
      "mod": "PRE",
      "lun": null,
      "mar": null,
      "mie": "13:00/14:50",
      "jue": null,
      "vie": null,
      "sab": null,
      "dom": null
    },
    {
      "nrc": "15003",
      "codigo": "UCAB-'00002'",
      "profesor": "Alarcón Matheus, Johan Alberto",
      "asignatura": "Identidad, Liderazgo y Compromiso II.",
      "tax": "TA1",
      "mod": "PRE",
      "lun": "13:00/14:50",
      "mar": null,
      "mie": null,
      "jue": null,
      "vie": null,
      "sab": null,
      "dom": null
    },
    {
      "nrc": "15004",
      "codigo": "UCAB-'00002'",
      "profesor": "Cadenas Quintero, Benedicto Javier",
      "asignatura": "Identidad, Liderazgo y Compromiso II.",
      "tax": "TA1",
      "mod": "PRE",
      "lun": null,
      "mar": "11:00/12:50",
      "mie": null,
      "jue": null,
      "vie": null,
      "sab": null,
      "dom": null
    },
    {
      "nrc": "15005",
      "codigo": "UCAB-'00002'",
      "profesor": "Afonso Dos Santos, Celsa",
      "asignatura": "Identidad, Liderazgo y Compromiso II.",
      "tax": "TA1",
      "mod": "PRE",
      "lun": null,
      "mar": "13:00/14:50",
      "mie": null,
      "jue": null,
      "vie": null,
      "sab": null,
      "dom": null
    },
    {
      "nrc": "15854",
      "codigo": "INFO-'02018'",
      "profesor": "Cardoso Militao, Lúcia Isabel",
      "asignatura": "Ingeniería de Requisitos.",
      "tax": "TA4E",
      "mod": "PRE",
      "lun": null,
      "mar": null,
      "mie": null,
      "jue": "10:00/12:50",
      "vie": null,
      "sab": null,
      "dom": null
    },
    {
      "nrc": "16850",
      "codigo": "INFO-'02018'",
      "profesor": "Cardoso Militao, Lúcia Isabel",
      "asignatura": "Ingeniería de Requisitos.",
      "tax": "TA4E",
      "mod": "PRE",
      "lun": null,
      "mar": null,
      "mie": null,
      "jue": "13:00/15:50",
      "vie": null,
      "sab": null,
      "dom": null
    },
    {
      "nrc": "15833",
      "codigo": "INFO-'02007'",
      "profesor": "Pérez de Ovalles, María Angélica",
      "asignatura": "Ingeniería de Software.",
      "tax": "TA4E",
      "mod": "PRE",
      "lun": null,
      "mar": "07:00/08:50",
      "mie": null,
      "jue": "09:00/10:50",
      "vie": null,
      "sab": null,
      "dom": null
    },
    {
      "nrc": "16014",
      "codigo": "INFO-'02007'",
      "profesor": "Pérez de Ovalles, María Angélica",
      "asignatura": "Ingeniería de Software.",
      "tax": "TA4E",
      "mod": "PRE",
      "lun": null,
      "mar": "09:00/10:50",
      "mie": null,
      "jue": "07:00/08:50",
      "vie": null,
      "sab": null,
      "dom": null
    },
    {
      "nrc": "15691",
      "codigo": "FING-'02016'",
      "profesor": "Quintero Davila, José Luis",
      "asignatura": "Ingeniería Económica.",
      "tax": "TA4",
      "mod": "PRE",
      "lun": null,
      "mar": null,
      "mie": null,
      "jue": null,
      "vie": "07:00/09:50",
      "sab": null,
      "dom": null
    },
    {
      "nrc": "16048",
      "codigo": "FING-'02016'",
      "profesor": "Quintero Davila, José Luis",
      "asignatura": "Ingeniería Económica.",
      "tax": "TA4",
      "mod": "PRE",
      "lun": null,
      "mar": null,
      "mie": "09:00/11:50",
      "jue": null,
      "vie": null,
      "sab": null,
      "dom": null
    },
    {
      "nrc": "17007",
      "codigo": "FING-'02016'",
      "profesor": "Por Asignar",
      "asignatura": "Ingeniería Económica.",
      "tax": "TA4",
      "mod": "PRE",
      "lun": "07:00/09:50",
      "mar": null,
      "mie": null,
      "jue": null,
      "vie": null,
      "sab": null,
      "dom": null
    },
    {
      "nrc": "15855",
      "codigo": "INFO-'02014'",
      "profesor": "Rivas García, Fredi Alfonso",
      "asignatura": "Inglés I.",
      "tax": "TA6",
      "mod": "PRE",
      "lun": null,
      "mar": null,
      "mie": "11:00/13:50",
      "jue": null,
      "vie": null,
      "sab": null,
      "dom": null
    },
    {
      "nrc": "15856",
      "codigo": "INFO-'02014'",
      "profesor": "Youssif Jorge, Rosa",
      "asignatura": "Inglés I.",
      "tax": "TA6",
      "mod": "PRE",
      "lun": null,
      "mar": null,
      "mie": null,
      "jue": "15:00/17:50",
      "vie": null,
      "sab": null,
      "dom": null
    },
    {
      "nrc": "15845",
      "codigo": "INFO-'02021'",
      "profesor": "González Nahmens, Amasilis del Carmen",
      "asignatura": "Inglés II.",
      "tax": "TA6",
      "mod": "PRE",
      "lun": null,
      "mar": "15:00/17:50",
      "mie": null,
      "jue": null,
      "vie": null,
      "sab": null,
      "dom": null
    },
    {
      "nrc": "15846",
      "codigo": "INFO-'02021'",
      "profesor": "González Nahmens, Amasilis del Carmen",
      "asignatura": "Inglés II.",
      "tax": "TA6",
      "mod": "PRE",
      "lun": null,
      "mar": null,
      "mie": "15:00/17:50",
      "jue": null,
      "vie": null,
      "sab": null,
      "dom": null
    },
    {
      "nrc": "15826",
      "codigo": "INFO-'02026'",
      "profesor": "Lista Mancilla, Olga Carolina",
      "asignatura": "Inglés Técnico.",
      "tax": "TA6",
      "mod": "VIT",
      "lun": null,
      "mar": null,
      "mie": null,
      "jue": null,
      "vie": "18:00/20:50",
      "sab": null,
      "dom": null
    },
    {
      "nrc": "16605",
      "codigo": "INFO-'02026'",
      "profesor": "Lista Mancilla, Olga Carolina",
      "asignatura": "Inglés Técnico.",
      "tax": "TA6",
      "mod": "VIT",
      "lun": null,
      "mar": null,
      "mie": null,
      "jue": null,
      "vie": null,
      "sab": "18:00/20:50",
      "dom": null
    },
    {
      "nrc": "15255",
      "codigo": "UCAB-'00008'",
      "profesor": "González Altuna, Hirwing del Carmen",
      "asignatura": "Innovación y Emprendimiento.",
      "tax": "TA1",
      "mod": "VRE",
      "lun": null,
      "mar": null,
      "mie": null,
      "jue": null,
      "vie": null,
      "sab": "07:00/08:50",
      "dom": null
    },
    {
      "nrc": "15256",
      "codigo": "UCAB-'00008'",
      "profesor": "González Altuna, Hirwing del Carmen",
      "asignatura": "Innovación y Emprendimiento.",
      "tax": "TA1",
      "mod": "VRE",
      "lun": null,
      "mar": null,
      "mie": null,
      "jue": null,
      "vie": null,
      "sab": null,
      "dom": "07:00/08:50"
    },
    {
      "nrc": "15257",
      "codigo": "UCAB-'00008'",
      "profesor": "González Bravo, Yoel Modesto",
      "asignatura": "Innovación y Emprendimiento.",
      "tax": "TA1",
      "mod": "VRE",
      "lun": null,
      "mar": null,
      "mie": null,
      "jue": null,
      "vie": null,
      "sab": "07:00/08:50",
      "dom": null
    },
    {
      "nrc": "15258",
      "codigo": "UCAB-'00008'",
      "profesor": "Sulbarán Hereira, Werner José",
      "asignatura": "Innovación y Emprendimiento.",
      "tax": "TA1",
      "mod": "VRE",
      "lun": null,
      "mar": null,
      "mie": null,
      "jue": null,
      "vie": null,
      "sab": "07:00/08:50",
      "dom": null
    },
    {
      "nrc": "15259",
      "codigo": "UCAB-'00008'",
      "profesor": "Sulbarán Hereira, Werner José",
      "asignatura": "Innovación y Emprendimiento.",
      "tax": "TA1",
      "mod": "VRE",
      "lun": null,
      "mar": null,
      "mie": null,
      "jue": null,
      "vie": null,
      "sab": null,
      "dom": "07:00/08:50"
    },
    {
      "nrc": "15260",
      "codigo": "UCAB-'00008'",
      "profesor": "Aponte Castillo, Scampola Carolina",
      "asignatura": "Innovación y Emprendimiento.",
      "tax": "TA1",
      "mod": "VRE",
      "lun": null,
      "mar": null,
      "mie": null,
      "jue": null,
      "vie": null,
      "sab": "07:00/08:50",
      "dom": null
    },
    {
      "nrc": "15261",
      "codigo": "UCAB-'00008'",
      "profesor": "Lanz Rodríguez, Adriana Carolina",
      "asignatura": "Innovación y Emprendimiento.",
      "tax": "TA1",
      "mod": "VRE",
      "lun": null,
      "mar": null,
      "mie": null,
      "jue": null,
      "vie": null,
      "sab": null,
      "dom": "07:00/08:50"
    },
    {
      "nrc": "15263",
      "codigo": "UCAB-'00008'",
      "profesor": "García Castro, Wladimir",
      "asignatura": "Innovación y Emprendimiento.",
      "tax": "TA1",
      "mod": "VRE",
      "lun": null,
      "mar": null,
      "mie": null,
      "jue": null,
      "vie": null,
      "sab": "07:00/08:50",
      "dom": null
    },
    {
      "nrc": "15971",
      "codigo": "UCAB-'00008'",
      "profesor": "Rodríguez Guerrero, Francisco José",
      "asignatura": "Innovación y Emprendimiento.",
      "tax": "TA1",
      "mod": "VRE",
      "lun": null,
      "mar": null,
      "mie": null,
      "jue": null,
      "vie": null,
      "sab": null,
      "dom": "07:00/08:50"
    },
    {
      "nrc": "16575",
      "codigo": "UCAB-'00008'",
      "profesor": "Barrios Álvarez, Jesús Enrique",
      "asignatura": "Innovación y Emprendimiento.",
      "tax": "TA1",
      "mod": "VRE",
      "lun": null,
      "mar": null,
      "mie": null,
      "jue": null,
      "vie": null,
      "sab": "07:00/08:50",
      "dom": null
    },
    {
      "nrc": "16576",
      "codigo": "UCAB-'00008'",
      "profesor": "Por Asignar",
      "asignatura": "Innovación y Emprendimiento.",
      "tax": "TA1",
      "mod": "VRE",
      "lun": null,
      "mar": null,
      "mie": null,
      "jue": null,
      "vie": null,
      "sab": null,
      "dom": null
    },
    {
      "nrc": "16577",
      "codigo": "UCAB-'00008'",
      "profesor": "Por Asignar",
      "asignatura": "Innovación y Emprendimiento.",
      "tax": "TA1",
      "mod": "VRE",
      "lun": null,
      "mar": null,
      "mie": null,
      "jue": null,
      "vie": null,
      "sab": null,
      "dom": null
    },
    {
      "nrc": "15992",
      "codigo": "INFO-'02020'",
      "profesor": "La Fontaine García, Gustavo Adolfo",
      "asignatura": "Inteligencia Artificial: Aprendizaje Automático.",
      "tax": "TA9",
      "mod": "PRE",
      "lun": null,
      "mar": "10:00/11:50",
      "mie": "11:00/12:50",
      "jue": null,
      "vie": null,
      "sab": null,
      "dom": null
    },
    {
      "nrc": "16782",
      "codigo": "INFO-'02020'",
      "profesor": "García León, Pedro José",
      "asignatura": "Inteligencia Artificial: Aprendizaje Automático.",
      "tax": "TA9",
      "mod": "PRE",
      "lun": null,
      "mar": null,
      "mie": "13:00/14:50",
      "jue": null,
      "vie": "10:00/11:50",
      "sab": null,
      "dom": null
    },
    {
      "nrc": "15857",
      "codigo": "INFO-'02024'",
      "profesor": "Di Vasta Valente, Concettina",
      "asignatura": "Inteligencia de Negocios.",
      "tax": "TA9",
      "mod": "PRE",
      "lun": "07:00/09:50",
      "mar": null,
      "mie": null,
      "jue": null,
      "vie": null,
      "sab": null,
      "dom": null
    },
    {
      "nrc": "15859",
      "codigo": "INFO-'02024'",
      "profesor": "Di Vasta Valente, Concettina",
      "asignatura": "Inteligencia de Negocios.",
      "tax": "TA9",
      "mod": "PRE",
      "lun": "10:00/12:50",
      "mar": null,
      "mie": null,
      "jue": null,
      "vie": null,
      "sab": null,
      "dom": null
    },
    {
      "nrc": "16896",
      "codigo": "INFO-'02024'",
      "profesor": "Djenanian Dertorossian, Armen",
      "asignatura": "Inteligencia de Negocios.",
      "tax": "TA9",
      "mod": "PRE",
      "lun": "10:00/12:50",
      "mar": null,
      "mie": null,
      "jue": null,
      "vie": null,
      "sab": null,
      "dom": null
    },
    {
      "nrc": "16400",
      "codigo": "INFO-'02008'",
      "profesor": "Gómez Chacón, Carlos Esteban",
      "asignatura": "Interacción Humano-Computador.",
      "tax": "TA4E",
      "mod": "PRE",
      "lun": null,
      "mar": "13:00/14:50",
      "mie": null,
      "jue": null,
      "vie": "16:00/17:50",
      "sab": null,
      "dom": null
    },
    {
      "nrc": "16571",
      "codigo": "INFO-'02008'",
      "profesor": "Gómez Chacón, Carlos Esteban",
      "asignatura": "Interacción Humano-Computador.",
      "tax": "TA4E",
      "mod": "PRE",
      "lun": null,
      "mar": null,
      "mie": "16:00/17:50",
      "jue": "13:00/14:50",
      "vie": null,
      "sab": null,
      "dom": null
    },
    {
      "nrc": "16009",
      "codigo": "INFO-'02022'",
      "profesor": "Quintero Davila, José Luis",
      "asignatura": "Investigación de Operaciones.",
      "tax": "TA4E",
      "mod": "PRE",
      "lun": "10:00/11:50",
      "mar": null,
      "mie": "07:00/08:50",
      "jue": null,
      "vie": null,
      "sab": null,
      "dom": null
    },
    {
      "nrc": "16783",
      "codigo": "INFO-'02022'",
      "profesor": "Becemberg Lippo, Rafael Enrique",
      "asignatura": "Investigación de Operaciones.",
      "tax": "TA4E",
      "mod": "PRE",
      "lun": null,
      "mar": "13:00/14:50",
      "mie": null,
      "jue": "14:00/15:50",
      "vie": null,
      "sab": null,
      "dom": null
    },
    {
      "nrc": "16522",
      "codigo": "FING-'02013'",
      "profesor": "García León, Pedro José",
      "asignatura": "Laboratorio de Física.",
      "tax": "TA9",
      "mod": "PRE",
      "lun": null,
      "mar": null,
      "mie": null,
      "jue": "07:00/08:50",
      "vie": null,
      "sab": null,
      "dom": null
    },
    {
      "nrc": "16523",
      "codigo": "FING-'02013'",
      "profesor": "Peraza Cabello, Francisco José",
      "asignatura": "Laboratorio de Física.",
      "tax": "TA9",
      "mod": "PRE",
      "lun": null,
      "mar": null,
      "mie": null,
      "jue": null,
      "vie": "14:00/15:50",
      "sab": null,
      "dom": null
    },
    {
      "nrc": "16884",
      "codigo": "FING-'02013'",
      "profesor": "Peraza Cabello, Francisco José",
      "asignatura": "Laboratorio de Física.",
      "tax": "TA9",
      "mod": "PRE",
      "lun": null,
      "mar": null,
      "mie": null,
      "jue": null,
      "vie": "16:00/17:50",
      "sab": null,
      "dom": null
    },
    {
      "nrc": "16885",
      "codigo": "FING-'02013'",
      "profesor": "Lárez Natera, Joszaira Del Valle",
      "asignatura": "Laboratorio de Física.",
      "tax": "TA9",
      "mod": "PRE",
      "lun": null,
      "mar": null,
      "mie": null,
      "jue": null,
      "vie": "10:00/11:50",
      "sab": null,
      "dom": null
    },
    {
      "nrc": "16143",
      "codigo": "FING-'02009'",
      "profesor": "Por Asignar",
      "asignatura": "Lógica.",
      "tax": "TA4E",
      "mod": "PRE",
      "lun": "08:00/08:50",
      "mar": null,
      "mie": null,
      "jue": "07:00/08:50",
      "vie": null,
      "sab": null,
      "dom": null
    },
    {
      "nrc": "16144",
      "codigo": "FING-'02009'",
      "profesor": "Por Asignar",
      "asignatura": "Lógica.",
      "tax": "TA4E",
      "mod": "PRE",
      "lun": "11:00/11:50",
      "mar": null,
      "mie": null,
      "jue": "11:00/12:50",
      "vie": null,
      "sab": null,
      "dom": null
    },
    {
      "nrc": "16846",
      "codigo": "FING-'02009'",
      "profesor": "Por Asignar",
      "asignatura": "Lógica.",
      "tax": "TA4E",
      "mod": "PRE",
      "lun": "14:00/14:50",
      "mar": null,
      "mie": null,
      "jue": "14:00/15:50",
      "vie": null,
      "sab": null,
      "dom": null
    },
    {
      "nrc": "16847",
      "codigo": "FING-'02009'",
      "profesor": "Por Asignar",
      "asignatura": "Lógica.",
      "tax": "TA4E",
      "mod": "PRE",
      "lun": "15:00/15:50",
      "mar": null,
      "mie": "14:00/15:50",
      "jue": null,
      "vie": null,
      "sab": null,
      "dom": null
    },
    {
      "nrc": "15839",
      "codigo": "INFO-'02000'",
      "profesor": "Martínez León, Henry José",
      "asignatura": "Matemáticas Discretas.",
      "tax": "TA4E",
      "mod": "PRE",
      "lun": "10:00/11:50",
      "mar": null,
      "mie": "07:00/07:50",
      "jue": "10:00/11:50",
      "vie": null,
      "sab": null,
      "dom": null
    },
    {
      "nrc": "15840",
      "codigo": "INFO-'02000'",
      "profesor": "Valencia Zambrano, Irving Alfredo",
      "asignatura": "Matemáticas Discretas.",
      "tax": "TA4E",
      "mod": "PRE",
      "lun": null,
      "mar": null,
      "mie": "10:00/11:50",
      "jue": "10:00/11:50",
      "vie": "07:00/07:50",
      "sab": null,
      "dom": null
    },
    {
      "nrc": "15884",
      "codigo": "INFO-'02000'",
      "profesor": "Varela Costa, María Teresa",
      "asignatura": "Matemáticas Discretas.",
      "tax": "TA4E",
      "mod": "PRE",
      "lun": "09:00/10:50",
      "mar": "10:00/11:50",
      "mie": null,
      "jue": null,
      "vie": "10:00/10:50",
      "sab": null,
      "dom": null
    },
    {
      "nrc": "15702",
      "codigo": "FING-'02010'",
      "profesor": "Alvarez Méndez, Adonahis Arlette",
      "asignatura": "Métodos Numéricos.",
      "tax": "TA9",
      "mod": "PRE",
      "lun": null,
      "mar": null,
      "mie": null,
      "jue": null,
      "vie": "11:00/12:50",
      "sab": null,
      "dom": null
    },
    {
      "nrc": "16494",
      "codigo": "FING-'02010'",
      "profesor": "Alvarez Méndez, Adonahis Arlette",
      "asignatura": "Métodos Numéricos.",
      "tax": "TA9",
      "mod": "PRE",
      "lun": null,
      "mar": null,
      "mie": null,
      "jue": null,
      "vie": "14:00/15:50",
      "sab": null,
      "dom": null
    },
    {
      "nrc": "17017",
      "codigo": "FING-'02010'",
      "profesor": "Por Asignar",
      "asignatura": "Métodos Numéricos.",
      "tax": "TA9",
      "mod": "PRE",
      "lun": null,
      "mar": null,
      "mie": null,
      "jue": "08:00/09:50",
      "vie": null,
      "sab": null,
      "dom": null
    },
    {
      "nrc": "17022",
      "codigo": "FING-'02010'",
      "profesor": "Alvarez Méndez, Adonahis Arlette",
      "asignatura": "Métodos Numéricos.",
      "tax": "TA9",
      "mod": "PRE",
      "lun": null,
      "mar": null,
      "mie": null,
      "jue": "15:00/16:50",
      "vie": null,
      "sab": null,
      "dom": null
    },
    {
      "nrc": "15355",
      "codigo": "ADCO-'00444'",
      "profesor": "Ferreira Fernandes, Freddy Raúl",
      "asignatura": "Neuromarketing.",
      "tax": "TA9",
      "mod": "PRE",
      "lun": null,
      "mar": "13:00/15:50",
      "mie": null,
      "jue": null,
      "vie": null,
      "sab": null,
      "dom": null
    },
    {
      "nrc": "15834",
      "codigo": "INFO-'02005'",
      "profesor": "Hernández Barrera, Omar Jesús",
      "asignatura": "Organización del Computador.",
      "tax": "TA4E",
      "mod": "PRE",
      "lun": "11:00/12:50",
      "mar": "13:00/14:50",
      "mie": null,
      "jue": null,
      "vie": null,
      "sab": null,
      "dom": null
    },
    {
      "nrc": "16012",
      "codigo": "INFO-'02005'",
      "profesor": "Hernández Barrera, Omar Jesús",
      "asignatura": "Organización del Computador.",
      "tax": "TA4E",
      "mod": "PRE",
      "lun": null,
      "mar": "11:00/12:50",
      "mie": "11:00/12:50",
      "jue": null,
      "vie": null,
      "sab": null,
      "dom": null
    },
    {
      "nrc": "16404",
      "codigo": "INFO-'02005'",
      "profesor": "Hernández Barrera, Omar Jesús",
      "asignatura": "Organización del Computador.",
      "tax": "TA4E",
      "mod": "PRE",
      "lun": "15:00/16:50",
      "mar": null,
      "mie": null,
      "jue": "11:00/12:50",
      "vie": null,
      "sab": null,
      "dom": null
    },
    {
      "nrc": "15346",
      "codigo": "ADCO-'00429'",
      "profesor": "Venegas Pereira, Gerardo Luis",
      "asignatura": "Planificación Estratégica.",
      "tax": "TA3",
      "mod": "VIT",
      "lun": null,
      "mar": null,
      "mie": null,
      "jue": null,
      "vie": null,
      "sab": null,
      "dom": "10:00/12:50"
    },
    {
      "nrc": "15117",
      "codigo": "ADCO-'00350'",
      "profesor": "Martínez Vivas, Valentina",
      "asignatura": "Principios de Marketing.",
      "tax": "TA1",
      "mod": "PRE",
      "lun": null,
      "mar": "07:00/09:50",
      "mie": null,
      "jue": null,
      "vie": null,
      "sab": null,
      "dom": null
    },
    {
      "nrc": "15475",
      "codigo": "ADCO-'00350'",
      "profesor": "Martínez Vivas, Valentina",
      "asignatura": "Principios de Marketing.",
      "tax": "TA1",
      "mod": "PRE",
      "lun": null,
      "mar": "13:00/15:50",
      "mie": null,
      "jue": null,
      "vie": null,
      "sab": null,
      "dom": null
    },
    {
      "nrc": "15570",
      "codigo": "FING-'02011'",
      "profesor": "Campos Marrero, José Miguel",
      "asignatura": "Probabilidad y Estadística.",
      "tax": "TA4",
      "mod": "PRE",
      "lun": null,
      "mar": "16:00/17:50",
      "mie": null,
      "jue": null,
      "vie": "16:00/17:50",
      "sab": null,
      "dom": null
    },
    {
      "nrc": "15966",
      "codigo": "FING-'02011'",
      "profesor": "Campos Marrero, José Miguel",
      "asignatura": "Probabilidad y Estadística.",
      "tax": "TA4",
      "mod": "PRE",
      "lun": null,
      "mar": null,
      "mie": "14:00/15:50",
      "jue": null,
      "vie": "14:00/15:50",
      "sab": null,
      "dom": null
    },
    {
      "nrc": "15832",
      "codigo": "INFO-'02006'",
      "profesor": "Africano Silva, Raikjars Hans",
      "asignatura": "Programación Orientada a la Web.",
      "tax": "TA9",
      "mod": "PRE",
      "lun": null,
      "mar": null,
      "mie": "07:00/09:50",
      "jue": null,
      "vie": null,
      "sab": null,
      "dom": null
    },
    {
      "nrc": "16013",
      "codigo": "INFO-'02006'",
      "profesor": "Lara Campos, Rafael Antonio",
      "asignatura": "Programación Orientada a la Web.",
      "tax": "TA9",
      "mod": "PRE",
      "lun": null,
      "mar": "15:00/17:50",
      "mie": null,
      "jue": null,
      "vie": null,
      "sab": null,
      "dom": null
    },
    {
      "nrc": "16409",
      "codigo": "INFO-'02006'",
      "profesor": "Lara Campos, Rafael Antonio",
      "asignatura": "Programación Orientada a la Web.",
      "tax": "TA9",
      "mod": "PRE",
      "lun": null,
      "mar": null,
      "mie": null,
      "jue": "15:00/17:50",
      "vie": null,
      "sab": null,
      "dom": null
    },
    {
      "nrc": "15835",
      "codigo": "INFO-'02003'",
      "profesor": "Dos Santos Da Corte, Danny Milton",
      "asignatura": "Programación Orientada a Objetos.",
      "tax": "TA9",
      "mod": "PRE",
      "lun": "08:00/10:50",
      "mar": null,
      "mie": null,
      "jue": null,
      "vie": null,
      "sab": null,
      "dom": null
    },
    {
      "nrc": "15836",
      "codigo": "INFO-'02003'",
      "profesor": "Mendoza, Lia Roxana",
      "asignatura": "Programación Orientada a Objetos.",
      "tax": "TA9",
      "mod": "PRE",
      "lun": "08:00/09:50",
      "mar": null,
      "mie": null,
      "jue": "08:00/09:50",
      "vie": null,
      "sab": null,
      "dom": null
    },
    {
      "nrc": "15993",
      "codigo": "INFO-'02003'",
      "profesor": "Mendoza, Lia Roxana",
      "asignatura": "Programación Orientada a Objetos.",
      "tax": "TA9",
      "mod": "PRE",
      "lun": null,
      "mar": null,
      "mie": "10:00/11:50",
      "jue": "13:00/14:50",
      "vie": null,
      "sab": null,
      "dom": null
    },
    {
      "nrc": "15994",
      "codigo": "INFO-'02003'",
      "profesor": "De Sousa De Abreu, Joselito Anselmo",
      "asignatura": "Programación Orientada a Objetos.",
      "tax": "TA9",
      "mod": "PRE",
      "lun": "14:00/15:50",
      "mar": null,
      "mie": null,
      "jue": "14:00/15:50",
      "vie": null,
      "sab": null,
      "dom": null
    },
    {
      "nrc": "17192",
      "codigo": "INFO-'02003'",
      "profesor": "Castillo Pacheco, José Gregorio",
      "asignatura": "Programación Orientada a Objetos.",
      "tax": "TA9",
      "mod": "PRE",
      "lun": "11:00/12:50",
      "mar": null,
      "mie": "12:00/13:50",
      "jue": null,
      "vie": null,
      "sab": null,
      "dom": null
    },
    {
      "nrc": "17292",
      "codigo": "INFO-'P2003'",
      "profesor": "Dos Santos Da Corte, Danny Milton",
      "asignatura": "Programación Orientada a Objetos (Práctica).",
      "tax": "TA0",
      "mod": "PRE",
      "lun": null,
      "mar": null,
      "mie": "08:00/10:50",
      "jue": null,
      "vie": null,
      "sab": null,
      "dom": null
    },
    {
      "nrc": "17293",
      "codigo": "INFO-'P2003'",
      "profesor": "Mendoza, Lia Roxana",
      "asignatura": "Programación Orientada a Objetos (Práctica).",
      "tax": "TA0",
      "mod": "PRE",
      "lun": null,
      "mar": "08:00/09:50",
      "mie": null,
      "jue": null,
      "vie": null,
      "sab": null,
      "dom": null
    },
    {
      "nrc": "17294",
      "codigo": "INFO-'P2003'",
      "profesor": "Mendoza, Lia Roxana",
      "asignatura": "Programación Orientada a Objetos (Práctica).",
      "tax": "TA0",
      "mod": "PRE",
      "lun": null,
      "mar": null,
      "mie": "13:00/14:50",
      "jue": null,
      "vie": null,
      "sab": null,
      "dom": null
    },
    {
      "nrc": "17295",
      "codigo": "INFO-'P2003'",
      "profesor": "Castillo Pacheco, José Gregorio",
      "asignatura": "Programación Orientada a Objetos (Práctica).",
      "tax": "TA0",
      "mod": "PRE",
      "lun": null,
      "mar": null,
      "mie": null,
      "jue": "12:00/13:50",
      "vie": null,
      "sab": null,
      "dom": null
    },
    {
      "nrc": "17296",
      "codigo": "INFO-'P2003'",
      "profesor": "De Sousa De Abreu, Joselito Anselmo",
      "asignatura": "Programación Orientada a Objetos (Práctica).",
      "tax": "TA0",
      "mod": "PRE",
      "lun": "16:00/17:50",
      "mar": null,
      "mie": null,
      "jue": null,
      "vie": null,
      "sab": null,
      "dom": null
    },
    {
      "nrc": "16410",
      "codigo": "INFO-'02016'",
      "profesor": "Russoniello Antonacci, Antonio",
      "asignatura": "Redes de Comunicación de Datos.",
      "tax": "TA9",
      "mod": "PRE",
      "lun": null,
      "mar": "09:00/11:50",
      "mie": null,
      "jue": null,
      "vie": null,
      "sab": null,
      "dom": null
    },
    {
      "nrc": "16794",
      "codigo": "INFO-'02016'",
      "profesor": "Murillo Gonzalez, Luz Karime",
      "asignatura": "Redes de Comunicación de Datos.",
      "tax": "TA9",
      "mod": "PRE",
      "lun": null,
      "mar": null,
      "mie": "08:00/10:50",
      "jue": null,
      "vie": null,
      "sab": null,
      "dom": null
    },
    {
      "nrc": "16421",
      "codigo": "INFO-'P2016'",
      "profesor": "Russoniello Antonacci, Antonio",
      "asignatura": "Redes de Comunicación de Datos (Práctica).",
      "tax": "TA0",
      "mod": "PRE",
      "lun": null,
      "mar": "12:00/13:50",
      "mie": null,
      "jue": null,
      "vie": null,
      "sab": null,
      "dom": null
    },
    {
      "nrc": "16422",
      "codigo": "INFO-'P2016'",
      "profesor": "Russoniello Antonacci, Antonio",
      "asignatura": "Redes de Comunicación de Datos (Práctica).",
      "tax": "TA0",
      "mod": "PRE",
      "lun": null,
      "mar": "16:00/17:50",
      "mie": null,
      "jue": null,
      "vie": null,
      "sab": null,
      "dom": null
    },
    {
      "nrc": "16795",
      "codigo": "INFO-'P2016'",
      "profesor": "Murillo Gonzalez, Luz Karime",
      "asignatura": "Redes de Comunicación de Datos (Práctica).",
      "tax": "TA0",
      "mod": "PRE",
      "lun": null,
      "mar": null,
      "mie": "11:00/12:50",
      "jue": null,
      "vie": null,
      "sab": null,
      "dom": null
    },
    {
      "nrc": "16796",
      "codigo": "INFO-'P2016'",
      "profesor": "Murillo Gonzalez, Luz Karime",
      "asignatura": "Redes de Comunicación de Datos (Práctica).",
      "tax": "TA0",
      "mod": "PRE",
      "lun": null,
      "mar": null,
      "mie": "14:00/15:50",
      "jue": null,
      "vie": null,
      "sab": null,
      "dom": null
    },
    {
      "nrc": "15827",
      "codigo": "INFO-'02012'",
      "profesor": "Fernandes Agrela, Ana Karina",
      "asignatura": "Sistemas de Bases de Datos.",
      "tax": "TA4E",
      "mod": "PRE",
      "lun": "09:00/10:50",
      "mar": "09:00/11:50",
      "mie": null,
      "jue": null,
      "vie": null,
      "sab": null,
      "dom": null
    },
    {
      "nrc": "15829",
      "codigo": "INFO-'02012'",
      "profesor": "Cardoso Militao, Lúcia Isabel",
      "asignatura": "Sistemas de Bases de Datos.",
      "tax": "TA4E",
      "mod": "PRE",
      "lun": null,
      "mar": "10:00/12:50",
      "mie": "12:00/13:50",
      "jue": null,
      "vie": null,
      "sab": null,
      "dom": null
    },
    {
      "nrc": "16854",
      "codigo": "INFO-'02012'",
      "profesor": "Cardoso Militao, Lúcia Isabel",
      "asignatura": "Sistemas de Bases de Datos.",
      "tax": "TA4E",
      "mod": "PRE",
      "lun": null,
      "mar": "13:00/15:50",
      "mie": "14:00/15:50",
      "jue": null,
      "vie": null,
      "sab": null,
      "dom": null
    },
    {
      "nrc": "16895",
      "codigo": "INFO-'02012'",
      "profesor": "Goncalves Da Silva, Marlene",
      "asignatura": "Sistemas de Bases de Datos.",
      "tax": "TA4E",
      "mod": "PRE",
      "lun": null,
      "mar": null,
      "mie": "11:00/12:50",
      "jue": null,
      "vie": "10:00/12:50",
      "sab": null,
      "dom": null
    },
    {
      "nrc": "15837",
      "codigo": "INFO-'02004'",
      "profesor": "Hernández de López, Fanny Xiomara",
      "asignatura": "Sistemas de Información.",
      "tax": "TA4E",
      "mod": "PRE",
      "lun": null,
      "mar": null,
      "mie": null,
      "jue": "09:00/11:50",
      "vie": null,
      "sab": null,
      "dom": null
    },
    {
      "nrc": "15861",
      "codigo": "INFO-'02004'",
      "profesor": "Ortega, Dinarle Milagro",
      "asignatura": "Sistemas de Información.",
      "tax": "TA4E",
      "mod": "PRE",
      "lun": null,
      "mar": "13:00/15:50",
      "mie": null,
      "jue": null,
      "vie": null,
      "sab": null,
      "dom": null
    },
    {
      "nrc": "16011",
      "codigo": "INFO-'02010'",
      "profesor": "Hernández Barrera, Omar Jesús",
      "asignatura": "Sistemas Operativos.",
      "tax": "TA4E",
      "mod": "PRE",
      "lun": "07:00/08:50",
      "mar": "07:00/08:50",
      "mie": null,
      "jue": null,
      "vie": null,
      "sab": null,
      "dom": null
    },
    {
      "nrc": "16407",
      "codigo": "INFO-'02010'",
      "profesor": "Bravo Viloria, Jhoberth Andrés",
      "asignatura": "Sistemas Operativos.",
      "tax": "TA4E",
      "mod": "PRE",
      "lun": "17:00/18:50",
      "mar": "17:00/18:50",
      "mie": null,
      "jue": null,
      "vie": null,
      "sab": null,
      "dom": null
    },
    {
      "nrc": "16852",
      "codigo": "INFO-'02010'",
      "profesor": "Lara Domínguez, Gustavo Adolfo",
      "asignatura": "Sistemas Operativos.",
      "tax": "TA4E",
      "mod": "PRE",
      "lun": "07:00/08:50",
      "mar": null,
      "mie": null,
      "jue": "08:00/09:50",
      "vie": null,
      "sab": null,
      "dom": null
    },
    {
      "nrc": "15830",
      "codigo": "INFO-'02011'",
      "profesor": "Nadal Chacón, Vanessa Valentina",
      "asignatura": "Tópicos Especiales de Programación.",
      "tax": "TA9",
      "mod": "PRE",
      "lun": null,
      "mar": null,
      "mie": "07:00/09:50",
      "jue": null,
      "vie": null,
      "sab": null,
      "dom": null
    },
    {
      "nrc": "15997",
      "codigo": "INFO-'02011'",
      "profesor": "Fuentes Salazar, Luis Reynaldo",
      "asignatura": "Tópicos Especiales de Programación.",
      "tax": "TA9",
      "mod": "PRE",
      "lun": null,
      "mar": null,
      "mie": null,
      "jue": "09:00/11:50",
      "vie": null,
      "sab": null,
      "dom": null
    },
    {
      "nrc": "17125",
      "codigo": "INFO-'02011'",
      "profesor": "León Espinoza, Yisheng",
      "asignatura": "Tópicos Especiales de Programación.",
      "tax": "TA9",
      "mod": "PRE",
      "lun": null,
      "mar": null,
      "mie": "10:00/12:50",
      "jue": null,
      "vie": null,
      "sab": null,
      "dom": null
    },
    {
      "nrc": "15864",
      "codigo": "INFO-'02017'",
      "profesor": "Djenanian Dertorossian, Armen",
      "asignatura": "Tópicos Especiales para la Gestión de Datos.",
      "tax": "TA4E",
      "mod": "PRE",
      "lun": "07:00/09:50",
      "mar": null,
      "mie": null,
      "jue": null,
      "vie": null,
      "sab": null,
      "dom": null
    }
  ],
  "pageMaxSize": 176,
  "pageOffset": 0,
  "sectionsFetchedCount": 176
}